AzurLaneToolLib/__init__.py
AzurLaneToolLib/data/__init__.py
AzurLaneToolLib/data/data_AZR_Lan.py
AzurLaneToolLib/mode/__init__.py
AzurLaneToolLib/mode/mode_BlP_Cal.py
AzurLaneToolLib/mode/mode_CME_Cal.py
AzurLaneToolLib/mode/mode_EXP_Cal.py
AzurLaneToolLib/mode/mode_FCS_Cal.py
AzurLaneToolLib/mode/mode_FLE_Tol.py
AzurLaneToolLib/mode/mode_KSN_Com.py
AzurLaneToolLib/mode/mode_MSC_Cal.py
AzurLaneToolLib/mode/mode_SRS_Ptl.py
AzurLaneToolLib-0.6.4.dist-info/LICENSE
AzurLaneToolLib-0.6.4.dist-info/METADATA
AzurLaneToolLib-0.6.4.dist-info/WHEEL
AzurLaneToolLib-0.6.4.dist-info/top_level.txt
AzurLaneToolLib-0.6.4.dist-info/zip-safe
AzurLaneToolLib-0.6.4.dist-info/RECORD
