Metadata-Version: 2.1
Name: AzurLaneToolLib
Version: 0.6.4
Summary: Tools lib for Azur Lane which game powered by ManJiu Shanghai
Home-page: https://github.com/thedayofthedoctor/altl
Author: Matt Belfast Brown
Author-email: thedayofthedo@gmail.com
License: GPL-3.0 LICENSE
Project-URL: Documentation, http://belfast.web3v.work/program/doc/altl/
Project-URL: Bug Tracker, https://github.com/thedayofthedoctor/altl/issues
Keywords: pip,azur_lane,tool
Platform: any
Classifier: Programming Language :: Python :: 3.7
Classifier: Programming Language :: Python :: 3.8
Classifier: Programming Language :: Python :: 3.9
Classifier: Programming Language :: Python :: 3.10
Classifier: Programming Language :: Python :: 3.11
Classifier: Programming Language :: Python :: 3.12
Classifier: License :: OSI Approved :: GNU General Public License v3 (GPLv3)
Requires-Python: >=3.7,<=3.12
License-File: LICENSE
Requires-Dist: lzstring
